ruamel.pdfdouble-0.1.2-py2.7-nspkg.pth
ruamel.pdfdouble-0.1.2.dist-info/namespace_packages.txt
ruamel.pdfdouble-0.1.2.dist-info/WHEEL
ruamel.pdfdouble-0.1.2.dist-info/top_level.txt
ruamel.pdfdouble-0.1.2.dist-info/RECORD
ruamel.pdfdouble-0.1.2.dist-info/metadata.json
ruamel.pdfdouble-0.1.2.dist-info/METADATA
ruamel.pdfdouble-0.1.2.dist-info/DESCRIPTION.rst
ruamel.pdfdouble-0.1.2.dist-info/entry_points.txt
ruamel.pdfdouble-0.1.2.dist-info/LICENSE.txt
ruamel/pdfdouble/pdfdouble.py
ruamel/pdfdouble/__init__.py
