Metadata-Version: 2.0
Name: ruamel.pdfdouble
Version: 0.1.2
Summary: scan and find double PDF files, by creating a hash database
Home-page: https://bitbucket.org/ruamel/pdfdouble
Author: Anthon van der Neut
Author-email: a.van.der.neut@ruamel.eu
License: MIT license
Platform: UNKNOWN
Classifier: Development Status :: 4 - Beta
Classifier: Intended Audience :: Developers
Classifier: License :: OSI Approved :: MIT License
Classifier: Operating System :: OS Independent
Classifier: Programming Language :: Python
Requires-Dist: ruamel.base (>=1.0.0)
Requires-Dist: ruamel.appconfig
